pettracer/__init__.py
pettracer/client.py
pettracer/py.typed
pettracer/types.py
pettracer_client-0.2.0.dist-info/licenses/LICENSE
pettracer_client-0.2.0.dist-info/METADATA
pettracer_client-0.2.0.dist-info/WHEEL
pettracer_client-0.2.0.dist-info/top_level.txt
pettracer_client-0.2.0.dist-info/RECORD
