Metadata-Version: 2.4
Name: pettracer-client
Version: 0.2.0
Summary: Python client library for the PetTracer GPS pet collar portal
Author-email: Richard Giles <git@egilius.net>
License: MIT
Project-URL: Homepage, https://github.com/AmbientArchitect/petTracer-API
Project-URL: Documentation, https://github.com/AmbientArchitect/petTracer-API#readme
Project-URL: Repository, https://github.com/AmbientArchitect/petTracer-API
Project-URL: Issues, https://github.com/AmbientArchitect/petTracer-API/issues
Keywords: pettracer,gps,pet,tracker,collar,api,client
Classifier: Development Status :: 4 - Beta
Classifier: Intended Audience :: Developers
Classifier: License :: OSI Approved :: MIT License
Classifier: Programming Language :: Python :: 3
Classifier: Programming Language :: Python :: 3.12
Classifier: Programming Language :: Python :: 3 :: Only
Classifier: Topic :: Software Development :: Libraries :: Python Modules
Classifier: Topic :: Home Automation
Classifier: Typing :: Typed
Requires-Python: >=3.12
License-File: LICENSE
Requires-Dist: aiohttp>=3.9.0
Provides-Extra: dev
Requires-Dist: pytest>=7.4.0; extra == "dev"
Requires-Dist: pytest-cov>=4.1.0; extra == "dev"
Requires-Dist: pytest-asyncio>=0.21.0; extra == "dev"
Dynamic: license-file
